[
 {
  "content": "<div>\n    <div style=\"text-align: center;\">\n        <img alt=\"Smiley face\" height=\"82\" src=\"/files/EMI LOGO-4.jpg\" style=\"line-height: 1.42857;\" width=\"82\"><span style=\"line-height: 1.42857;\">\u00a0\u00a0</span><b style=\"font-size: 24px; line-height: 1.3em; text-align: center;\">EVEREST METAL INDUSTRIES L.L.C.</b>\n\n        <img height=\"82\" src=\"/files/EMI_ISO.jpg\" style=\"line-height: 1.42857;\" width=\"82\">\n        <br style=\"line-height: 1.42857;\">\n    </div>\n</div>\n<div>\n    <hr>\n    <div style=\"text-align: center;\">\u00a0 \u00a0 \u00a0 \u00a0 \u00a0 \u00a0 \u00a0 \u00a0 DUBAI OFFICE \u00a0 \u00a0 \u00a0 \u00a0: P.O.BOX 283177, TEL:0097148877505, FAX : 0097148877541</div>\n    <div style=\"text-align: center;\">\u00a0 \u00a0 \u00a0 \u00a0 \u00a0 \u00a0 \u00a0 \u00a0 ABU DHABI OFFICE \u00a0 : P.O BOX 53837, TEL :00971 2 6413739, FAX : 00971 2 6413794</div>\n    <div style=\"text-align: center;\">\u00a0 \u00a0 \u00a0 \u00a0 \u00a0 \u00a0 \u00a0 \u00a0 \u00a0 \u00a0 \u00a0 \u00a0 \u00a0 \u00a0 \u00a0 \u00a0 \u00a0 \u00a0 TRADE LICENCE NO : 631162, INDUSTRIAL LICENCE NO :3279</div>\n</div>", 
  "disabled": 0, 
  "docstatus": 0, 
  "doctype": "Letter Head", 
  "footer": "<hr><blockquote style=\"margin: 0 0 0 40px; border: none; padding: 0px;\"><div style=\"text-align: center;\"><span style=\"line-height: 1.42857;\">ABU DHABI: P.O.BOX: 53837, ABU DHABI - U .A.E. TEL: 00971 2 6413739, FAX: 00971 2 6413794</span></div></blockquote>", 
  "is_default": 1, 
  "letter_head_name": "Everest", 
  "modified": "2017-02-03 14:59:36.415177", 
  "name": "Everest"
 }
]